gocd/__init__.py
gocd/server.py
gocd/api/__init__.py
gocd/api/artifact.py
gocd/api/endpoint.py
gocd/api/pipeline.py
gocd/api/pipeline_config.py
gocd/api/pipeline_groups.py
gocd/api/pluggable_scm.py
gocd/api/response.py
gocd/api/stage.py
gocd/api/template_config.py
gocd/vendor/__init__.py
gocd/vendor/multidimensional_urlencode/__init__.py
gocd/vendor/multidimensional_urlencode/urlencoder.py
gocd/vendor/multidimensional_urlencode/tests/__init__.py
gocd/vendor/multidimensional_urlencode/tests/test_urlencode.py
gocd_bridge-0.15.2.dist-info/DESCRIPTION.rst
gocd_bridge-0.15.2.dist-info/METADATA
gocd_bridge-0.15.2.dist-info/RECORD
gocd_bridge-0.15.2.dist-info/WHEEL
gocd_bridge-0.15.2.dist-info/metadata.json
gocd_bridge-0.15.2.dist-info/top_level.txt
